{
  "matches": {
    "match": [
      {
        "id": "67893082",
        "uuid": "f4cf4dea-2514-447c-a70c-8229e601fe84",
        "number": "1",
        "date": "27.01.2024",
        "time": "10:00",
        "delayPossible": "false",
        "decidingMatch": "false",
        "indefinitelyRescheduled": "false",
        "gameReassessed": "false",
        "host": {
          "id": "67669417",
          "uuid": "58963060-8036-49f6-a872-42d3db12ff7c",
          "name": "VC Offenburg 1",
          "club": "VC Offenburg"
        },
        "team": [
          {
            "number": "1",
            "id": "67669415",
            "uuid": "99260fd2-b6c3-4f8b-86b1-d2a35372f98e",
            "seasonTeamId": "27860233",
            "name": "TV Gundelfingen 1",
            "shortName": null,
            "clubCode": null,
            "club": {
              "name": "TV Gundelfingen",
              "shortName": null
            }
          },
          {
            "number": "2",
            "id": "67669414",
            "uuid": "1621288b-2251-4797-a9c2-66ac1d1b2d3b",
            "seasonTeamId": "27860249",
            "name": "FT 1844 Freiburg 2",
            "shortName": "FT 1844 2",
            "clubCode": null,
            "club": {
              "name": "FT 1844 Freiburg",
              "shortName": null
            }
          }
        ],
        "matchSeries": {
          "id": "67565880",
          "uuid": "e945695f-d642-4cd3-886d-2c679cc45681",
          "allSeasonId": "27a326bf-f46a-4e4c-92a4-4f6c43b99ca8",
          "name": "U14 weiblich - Quali 1 am 27.1.24",
          "shortName": "Q2_U14_w",
          "type": "Competition",
          "updated": "2024-03-04 14:54:24.91",
          "structureUpdated": "2024-01-29 11:43:53.347",
          "resultsUpdated": "2024-01-27 17:01:10.752",
          "season": {
            "id": "52761843",
            "uuid": "dfcaac22-776e-4c3c-b3a8-0c34c5a51558",
            "name": "2023/24"
          },
          "hierarchy": {
            "id": "67565864",
            "uuid": "ad1e803f-1985-4939-a566-168d4440881b",
            "name": "Quali-Turniere Jugendmeisterschaften",
            "shortName": "Quali",
            "hierarchyLevel": "3"
          },
          "fullHierarchy": {
            "hierarchy": [
              {
                "id": "67565864",
                "name": "Quali-Turniere Jugendmeisterschaften",
                "shortName": "Quali",
                "hierarchyLevel": "3"
              },
              {
                "id": "67565828",
                "name": "SBVV-Jugendmeisterschaften",
                "shortName": "sbvv_jm",
                "hierarchyLevel": "2"
              },
              {
                "id": "62752642",
                "name": "Jugendspielbetrieb",
                "shortName": "JUG",
                "hierarchyLevel": "1"
              },
              {
                "id": "62752550",
                "name": "Südbadischer Volleyball-Verband (SBVV)",
                "shortName": "SBVV",
                "hierarchyLevel": "0"
              }
            ]
          },
          "association": {
            "name": "Südbadischer Volleyball-Verband",
            "shortName": "SBVV"
          }
        },
        "location": {
          "id": "13906446",
          "name": "Sporthalle Nord-West",
          "street": "Otto-Hahn-Str. 3",
          "extraField": "-",
          "postalCode": "77656",
          "city": "Offenburg",
          "note": "-"
        },
        "referees": null,
        "results": {
          "winner": "2",
          "setPoints": "0:2",
          "ballPoints": "24:50",
          "sets": {
            "set": [
              {
                "number": "1",
                "points": "15:25",
                "winner": "TEAM2",
                "duration": "-"
              },
              {
                "number": "2",
                "points": "9:25",
                "winner": "TEAM2",
                "duration": "-"
              }
            ]
          },
          "verified": "false"
        },
        "spectators": "-",
        "netDuration": "-",
        "dateObject": "2024-01-27T09:00:00.000Z",
        "dateIso": "2024-01-27T09:00:00.000Z"
      },
      {
        "id": "67893086",
        "uuid": "d6cd5b2b-1528-4773-9d29-72e4bc785635",
        "number": "2",
        "date": "27.01.2024",
        "time": "10:00",
        "delayPossible": "false",
        "decidingMatch": "false",
        "indefinitelyRescheduled": "false",
        "gameReassessed": "false",
        "host": {
          "id": "67669417",
          "uuid": "58963060-8036-49f6-a872-42d3db12ff7c",
          "name": "VC Offenburg 1",
          "club": "VC Offenburg"
        },
        "team": [
          {
            "number": "1",
            "id": "67669416",
            "uuid": "f16afa47-a512-49d0-aa1d-847578faaefe",
            "seasonTeamId": "27860239",
            "name": "VC Müllheim",
            "shortName": null,
            "clubCode": null,
            "club": {
              "name": "VC Müllheim",
              "shortName": null
            }
          },
          {
            "number": "2",
            "id": "67669421",
            "uuid": "336bb69c-c80c-4160-aeb2-bbbfdf163d4a",
            "seasonTeamId": "27860247",
            "name": "VfR Umkirch",
            "shortName": null,
            "clubCode": null,
            "club": {
              "name": "VfR Umkirch",
              "shortName": null
            }
          }
        ],
        "matchSeries": {
          "id": "67565880",
          "uuid": "e945695f-d642-4cd3-886d-2c679cc45681",
          "allSeasonId": "27a326bf-f46a-4e4c-92a4-4f6c43b99ca8",
          "name": "U14 weiblich - Quali 1 am 27.1.24",
          "shortName": "Q2_U14_w",
          "type": "Competition",
          "updated": "2024-03-04 14:54:24.91",
          "structureUpdated": "2024-01-29 11:43:53.347",
          "resultsUpdated": "2024-01-27 17:01:10.752",
          "season": {
            "id": "52761843",
            "uuid": "dfcaac22-776e-4c3c-b3a8-0c34c5a51558",
            "name": "2023/24"
          },
          "hierarchy": {
            "id": "67565864",
            "uuid": "ad1e803f-1985-4939-a566-168d4440881b",
            "name": "Quali-Turniere Jugendmeisterschaften",
            "shortName": "Quali",
            "hierarchyLevel": "3"
          },
          "fullHierarchy": {
            "hierarchy": [
              {
                "id": "67565864",
                "name": "Quali-Turniere Jugendmeisterschaften",
                "shortName": "Quali",
                "hierarchyLevel": "3"
              },
              {
                "id": "67565828",
                "name": "SBVV-Jugendmeisterschaften",
                "shortName": "sbvv_jm",
                "hierarchyLevel": "2"
              },
              {
                "id": "62752642",
                "name": "Jugendspielbetrieb",
                "shortName": "JUG",
                "hierarchyLevel": "1"
              },
              {
                "id": "62752550",
                "name": "Südbadischer Volleyball-Verband (SBVV)",
                "shortName": "SBVV",
                "hierarchyLevel": "0"
              }
            ]
          },
          "association": {
            "name": "Südbadischer Volleyball-Verband",
            "shortName": "SBVV"
          }
        },
        "location": {
          "id": "13906446",
          "name": "Sporthalle Nord-West",
          "street": "Otto-Hahn-Str. 3",
          "extraField": "-",
          "postalCode": "77656",
          "city": "Offenburg",
          "note": "-"
        },
        "referees": null,
        "results": {
          "winner": "1",
          "setPoints": "2:1",
          "ballPoints": "62:52",
          "sets": {
            "set": [
              {
                "number": "1",
                "points": "25:17",
                "winner": "TEAM1",
                "duration": "-"
              },
              {
                "number": "2",
                "points": "22:25",
                "winner": "TEAM2",
                "duration": "-"
              },
              {
                "number": "3",
                "points": "15:10",
                "winner": "TEAM1",
                "duration": "-"
              }
            ]
          },
          "verified": "false"
        },
        "spectators": "-",
        "netDuration": "-",
        "dateObject": "2024-01-27T09:00:00.000Z",
        "dateIso": "2024-01-27T09:00:00.000Z"
      },
      {
        "id": "67893090",
        "uuid": "4a5398ed-736e-4618-8f6f-9719d322fbb7",
        "number": "3",
        "date": "27.01.2024",
        "time": "11:00",
        "delayPossible": "false",
        "decidingMatch": "false",
        "indefinitelyRescheduled": "false",
        "gameReassessed": "false",
        "host": {
          "id": "67669417",
          "uuid": "58963060-8036-49f6-a872-42d3db12ff7c",
          "name": "VC Offenburg 1",
          "club": "VC Offenburg"
        },
        "team": [
          {
            "number": "1",
            "id": "67669415",
            "uuid": "99260fd2-b6c3-4f8b-86b1-d2a35372f98e",
            "seasonTeamId": "27860233",
            "name": "TV Gundelfingen 1",
            "shortName": null,
            "clubCode": null,
            "club": {
              "name": "TV Gundelfingen",
              "shortName": null
            }
          },
          {
            "number": "2",
            "id": "67669416",
            "uuid": "f16afa47-a512-49d0-aa1d-847578faaefe",
            "seasonTeamId": "27860239",
            "name": "VC Müllheim",
            "shortName": null,
            "clubCode": null,
            "club": {
              "name": "VC Müllheim",
              "shortName": null
            }
          }
        ],
        "matchSeries": {
          "id": "67565880",
          "uuid": "e945695f-d642-4cd3-886d-2c679cc45681",
          "allSeasonId": "27a326bf-f46a-4e4c-92a4-4f6c43b99ca8",
          "name": "U14 weiblich - Quali 1 am 27.1.24",
          "shortName": "Q2_U14_w",
          "type": "Competition",
          "updated": "2024-03-04 14:54:24.91",
          "structureUpdated": "2024-01-29 11:43:53.347",
          "resultsUpdated": "2024-01-27 17:01:10.752",
          "season": {
            "id": "52761843",
            "uuid": "dfcaac22-776e-4c3c-b3a8-0c34c5a51558",
            "name": "2023/24"
          },
          "hierarchy": {
            "id": "67565864",
            "uuid": "ad1e803f-1985-4939-a566-168d4440881b",
            "name": "Quali-Turniere Jugendmeisterschaften",
            "shortName": "Quali",
            "hierarchyLevel": "3"
          },
          "fullHierarchy": {
            "hierarchy": [
              {
                "id": "67565864",
                "name": "Quali-Turniere Jugendmeisterschaften",
                "shortName": "Quali",
                "hierarchyLevel": "3"
              },
              {
                "id": "67565828",
                "name": "SBVV-Jugendmeisterschaften",
                "shortName": "sbvv_jm",
                "hierarchyLevel": "2"
              },
              {
                "id": "62752642",
                "name": "Jugendspielbetrieb",
                "shortName": "JUG",
                "hierarchyLevel": "1"
              },
              {
                "id": "62752550",
                "name": "Südbadischer Volleyball-Verband (SBVV)",
                "shortName": "SBVV",
                "hierarchyLevel": "0"
              }
            ]
          },
          "association": {
            "name": "Südbadischer Volleyball-Verband",
            "shortName": "SBVV"
          }
        },
        "location": {
          "id": "13906446",
          "name": "Sporthalle Nord-West",
          "street": "Otto-Hahn-Str. 3",
          "extraField": "-",
          "postalCode": "77656",
          "city": "Offenburg",
          "note": "-"
        },
        "referees": null,
        "results": {
          "winner": "2",
          "setPoints": "0:2",
          "ballPoints": "38:50",
          "sets": {
            "set": [
              {
                "number": "1",
                "points": "22:25",
                "winner": "TEAM2",
                "duration": "-"
              },
              {
                "number": "2",
                "points": "16:25",
                "winner": "TEAM2",
                "duration": "-"
              }
            ]
          },
          "verified": "false"
        },
        "spectators": "-",
        "netDuration": "-",
        "dateObject": "2024-01-27T10:00:00.000Z",
        "dateIso": "2024-01-27T10:00:00.000Z"
      },
      {
        "id": "67893107",
        "uuid": "69957ac6-1632-4fed-ae57-75b02d2d37cd",
        "number": "7",
        "date": "27.01.2024",
        "time": "11:00",
        "delayPossible": "false",
        "decidingMatch": "false",
        "indefinitelyRescheduled": "false",
        "gameReassessed": "false",
        "host": {
          "id": "67669417",
          "uuid": "58963060-8036-49f6-a872-42d3db12ff7c",
          "name": "VC Offenburg 1",
          "club": "VC Offenburg"
        },
        "team": [
          {
            "number": "1",
            "id": "67669417",
            "uuid": "58963060-8036-49f6-a872-42d3db12ff7c",
            "seasonTeamId": "27860243",
            "name": "VC Offenburg 1",
            "shortName": null,
            "clubCode": null,
            "club": {
              "name": "VC Offenburg",
              "shortName": null
            }
          },
          {
            "number": "2",
            "id": "67669418",
            "uuid": "b73f1c49-975d-4e3b-9106-e5fa8d801738",
            "seasonTeamId": "27860236",
            "name": "VC Weil",
            "shortName": null,
            "clubCode": null,
            "club": {
              "name": "VC Weil",
              "shortName": null
            }
          }
        ],
        "matchSeries": {
          "id": "67565880",
          "uuid": "e945695f-d642-4cd3-886d-2c679cc45681",
          "allSeasonId": "27a326bf-f46a-4e4c-92a4-4f6c43b99ca8",
          "name": "U14 weiblich - Quali 1 am 27.1.24",
          "shortName": "Q2_U14_w",
          "type": "Competition",
          "updated": "2024-03-04 14:54:24.91",
          "structureUpdated": "2024-01-29 11:43:53.347",
          "resultsUpdated": "2024-01-27 17:01:10.752",
          "season": {
            "id": "52761843",
            "uuid": "dfcaac22-776e-4c3c-b3a8-0c34c5a51558",
            "name": "2023/24"
          },
          "hierarchy": {
            "id": "67565864",
            "uuid": "ad1e803f-1985-4939-a566-168d4440881b",
            "name": "Quali-Turniere Jugendmeisterschaften",
            "shortName": "Quali",
            "hierarchyLevel": "3"
          },
          "fullHierarchy": {
            "hierarchy": [
              {
                "id": "67565864",
                "name": "Quali-Turniere Jugendmeisterschaften",
                "shortName": "Quali",
                "hierarchyLevel": "3"
              },
              {
                "id": "67565828",
                "name": "SBVV-Jugendmeisterschaften",
                "shortName": "sbvv_jm",
                "hierarchyLevel": "2"
              },
              {
                "id": "62752642",
                "name": "Jugendspielbetrieb",
                "shortName": "JUG",
                "hierarchyLevel": "1"
              },
              {
                "id": "62752550",
                "name": "Südbadischer Volleyball-Verband (SBVV)",
                "shortName": "SBVV",
                "hierarchyLevel": "0"
              }
            ]
          },
          "association": {
            "name": "Südbadischer Volleyball-Verband",
            "shortName": "SBVV"
          }
        },
        "location": {
          "id": "13906446",
          "name": "Sporthalle Nord-West",
          "street": "Otto-Hahn-Str. 3",
          "extraField": "-",
          "postalCode": "77656",
          "city": "Offenburg",
          "note": "-"
        },
        "referees": null,
        "results": {
          "winner": "1",
          "setPoints": "2:0",
          "ballPoints": "50:19",
          "sets": {
            "set": [
              {
                "number": "1",
                "points": "25:12",
                "winner": "TEAM1",
                "duration": "-"
              },
              {
                "number": "2",
                "points": "25:7",
                "winner": "TEAM1",
                "duration": "-"
              }
            ]
          },
          "verified": "false"
        },
        "spectators": "-",
        "netDuration": "-",
        "dateObject": "2024-01-27T10:00:00.000Z",
        "dateIso": "2024-01-27T10:00:00.000Z"
      },
      {
        "id": "67893094",
        "uuid": "cac18633-72cd-46d8-8bff-15630c043aa3",
        "number": "4",
        "date": "27.01.2024",
        "time": "12:00",
        "delayPossible": "false",
        "decidingMatch": "false",
        "indefinitelyRescheduled": "false",
        "gameReassessed": "false",
        "host": {
          "id": "67669417",
          "uuid": "58963060-8036-49f6-a872-42d3db12ff7c",
          "name": "VC Offenburg 1",
          "club": "VC Offenburg"
        },
        "team": [
          {
            "number": "1",
            "id": "67669414",
            "uuid": "1621288b-2251-4797-a9c2-66ac1d1b2d3b",
            "seasonTeamId": "27860249",
            "name": "FT 1844 Freiburg 2",
            "shortName": "FT 1844 2",
            "clubCode": null,
            "club": {
              "name": "FT 1844 Freiburg",
              "shortName": null
            }
          },
          {
            "number": "2",
            "id": "67669421",
            "uuid": "336bb69c-c80c-4160-aeb2-bbbfdf163d4a",
            "seasonTeamId": "27860247",
            "name": "VfR Umkirch",
            "shortName": null,
            "clubCode": null,
            "club": {
              "name": "VfR Umkirch",
              "shortName": null
            }
          }
        ],
        "matchSeries": {
          "id": "67565880",
          "uuid": "e945695f-d642-4cd3-886d-2c679cc45681",
          "allSeasonId": "27a326bf-f46a-4e4c-92a4-4f6c43b99ca8",
          "name": "U14 weiblich - Quali 1 am 27.1.24",
          "shortName": "Q2_U14_w",
          "type": "Competition",
          "updated": "2024-03-04 14:54:24.91",
          "structureUpdated": "2024-01-29 11:43:53.347",
          "resultsUpdated": "2024-01-27 17:01:10.752",
          "season": {
            "id": "52761843",
            "uuid": "dfcaac22-776e-4c3c-b3a8-0c34c5a51558",
            "name": "2023/24"
          },
          "hierarchy": {
            "id": "67565864",
            "uuid": "ad1e803f-1985-4939-a566-168d4440881b",
            "name": "Quali-Turniere Jugendmeisterschaften",
            "shortName": "Quali",
            "hierarchyLevel": "3"
          },
          "fullHierarchy": {
            "hierarchy": [
              {
                "id": "67565864",
                "name": "Quali-Turniere Jugendmeisterschaften",
                "shortName": "Quali",
                "hierarchyLevel": "3"
              },
              {
                "id": "67565828",
                "name": "SBVV-Jugendmeisterschaften",
                "shortName": "sbvv_jm",
                "hierarchyLevel": "2"
              },
              {
                "id": "62752642",
                "name": "Jugendspielbetrieb",
                "shortName": "JUG",
                "hierarchyLevel": "1"
              },
              {
                "id": "62752550",
                "name": "Südbadischer Volleyball-Verband (SBVV)",
                "shortName": "SBVV",
                "hierarchyLevel": "0"
              }
            ]
          },
          "association": {
            "name": "Südbadischer Volleyball-Verband",
            "shortName": "SBVV"
          }
        },
        "location": {
          "id": "13906446",
          "name": "Sporthalle Nord-West",
          "street": "Otto-Hahn-Str. 3",
          "extraField": "-",
          "postalCode": "77656",
          "city": "Offenburg",
          "note": "-"
        },
        "referees": null,
        "results": {
          "winner": "1",
          "setPoints": "2:0",
          "ballPoints": "50:24",
          "sets": {
            "set": [
              {
                "number": "1",
                "points": "25:13",
                "winner": "TEAM1",
                "duration": "-"
              },
              {
                "number": "2",
                "points": "25:11",
                "winner": "TEAM1",
                "duration": "-"
              }
            ]
          },
          "verified": "false"
        },
        "spectators": "-",
        "netDuration": "-",
        "dateObject": "2024-01-27T11:00:00.000Z",
        "dateIso": "2024-01-27T11:00:00.000Z"
      },
      {
        "id": "67893111",
        "uuid": "1d0023ce-7b74-4901-b02b-1fabc7e6fd42",
        "number": "8",
        "date": "27.01.2024",
        "time": "12:00",
        "delayPossible": "false",
        "decidingMatch": "false",
        "indefinitelyRescheduled": "false",
        "gameReassessed": "false",
        "host": {
          "id": "67669417",
          "uuid": "58963060-8036-49f6-a872-42d3db12ff7c",
          "name": "VC Offenburg 1",
          "club": "VC Offenburg"
        },
        "team": [
          {
            "number": "1",
            "id": "67669417",
            "uuid": "58963060-8036-49f6-a872-42d3db12ff7c",
            "seasonTeamId": "27860243",
            "name": "VC Offenburg 1",
            "shortName": null,
            "clubCode": null,
            "club": {
              "name": "VC Offenburg",
              "shortName": null
            }
          },
          {
            "number": "2",
            "id": "67669419",
            "uuid": "3ee8859f-1226-41e1-9076-befe50cb7134",
            "seasonTeamId": "27860241",
            "name": "FT 1844 Freiburg 1",
            "shortName": "FT 1844 1",
            "clubCode": null,
            "club": {
              "name": "FT 1844 Freiburg",
              "shortName": null
            }
          }
        ],
        "matchSeries": {
          "id": "67565880",
          "uuid": "e945695f-d642-4cd3-886d-2c679cc45681",
          "allSeasonId": "27a326bf-f46a-4e4c-92a4-4f6c43b99ca8",
          "name": "U14 weiblich - Quali 1 am 27.1.24",
          "shortName": "Q2_U14_w",
          "type": "Competition",
          "updated": "2024-03-04 14:54:24.91",
          "structureUpdated": "2024-01-29 11:43:53.347",
          "resultsUpdated": "2024-01-27 17:01:10.752",
          "season": {
            "id": "52761843",
            "uuid": "dfcaac22-776e-4c3c-b3a8-0c34c5a51558",
            "name": "2023/24"
          },
          "hierarchy": {
            "id": "67565864",
            "uuid": "ad1e803f-1985-4939-a566-168d4440881b",
            "name": "Quali-Turniere Jugendmeisterschaften",
            "shortName": "Quali",
            "hierarchyLevel": "3"
          },
          "fullHierarchy": {
            "hierarchy": [
              {
                "id": "67565864",
                "name": "Quali-Turniere Jugendmeisterschaften",
                "shortName": "Quali",
                "hierarchyLevel": "3"
              },
              {
                "id": "67565828",
                "name": "SBVV-Jugendmeisterschaften",
                "shortName": "sbvv_jm",
                "hierarchyLevel": "2"
              },
              {
                "id": "62752642",
                "name": "Jugendspielbetrieb",
                "shortName": "JUG",
                "hierarchyLevel": "1"
              },
              {
                "id": "62752550",
                "name": "Südbadischer Volleyball-Verband (SBVV)",
                "shortName": "SBVV",
                "hierarchyLevel": "0"
              }
            ]
          },
          "association": {
            "name": "Südbadischer Volleyball-Verband",
            "shortName": "SBVV"
          }
        },
        "location": {
          "id": "13906446",
          "name": "Sporthalle Nord-West",
          "street": "Otto-Hahn-Str. 3",
          "extraField": "-",
          "postalCode": "77656",
          "city": "Offenburg",
          "note": "-"
        },
        "referees": null,
        "results": {
          "winner": "1",
          "setPoints": "2:0",
          "ballPoints": "50:17",
          "sets": {
            "set": [
              {
                "number": "1",
                "points": "25:7",
                "winner": "TEAM1",
                "duration": "-"
              },
              {
                "number": "2",
                "points": "25:10",
                "winner": "TEAM1",
                "duration": "-"
              }
            ]
          },
          "verified": "false"
        },
        "spectators": "-",
        "netDuration": "-",
        "dateObject": "2024-01-27T11:00:00.000Z",
        "dateIso": "2024-01-27T11:00:00.000Z"
      },
      {
        "id": "67893098",
        "uuid": "e7f8767e-ec06-4d6a-9095-0b664a56e04c",
        "number": "5",
        "date": "27.01.2024",
        "time": "13:00",
        "delayPossible": "false",
        "decidingMatch": "false",
        "indefinitelyRescheduled": "false",
        "gameReassessed": "false",
        "host": {
          "id": "67669417",
          "uuid": "58963060-8036-49f6-a872-42d3db12ff7c",
          "name": "VC Offenburg 1",
          "club": "VC Offenburg"
        },
        "team": [
          {
            "number": "1",
            "id": "67669415",
            "uuid": "99260fd2-b6c3-4f8b-86b1-d2a35372f98e",
            "seasonTeamId": "27860233",
            "name": "TV Gundelfingen 1",
            "shortName": null,
            "clubCode": null,
            "club": {
              "name": "TV Gundelfingen",
              "shortName": null
            }
          },
          {
            "number": "2",
            "id": "67669421",
            "uuid": "336bb69c-c80c-4160-aeb2-bbbfdf163d4a",
            "seasonTeamId": "27860247",
            "name": "VfR Umkirch",
            "shortName": null,
            "clubCode": null,
            "club": {
              "name": "VfR Umkirch",
              "shortName": null
            }
          }
        ],
        "matchSeries": {
          "id": "67565880",
          "uuid": "e945695f-d642-4cd3-886d-2c679cc45681",
          "allSeasonId": "27a326bf-f46a-4e4c-92a4-4f6c43b99ca8",
          "name": "U14 weiblich - Quali 1 am 27.1.24",
          "shortName": "Q2_U14_w",
          "type": "Competition",
          "updated": "2024-03-04 14:54:24.91",
          "structureUpdated": "2024-01-29 11:43:53.347",
          "resultsUpdated": "2024-01-27 17:01:10.752",
          "season": {
            "id": "52761843",
            "uuid": "dfcaac22-776e-4c3c-b3a8-0c34c5a51558",
            "name": "2023/24"
          },
          "hierarchy": {
            "id": "67565864",
            "uuid": "ad1e803f-1985-4939-a566-168d4440881b",
            "name": "Quali-Turniere Jugendmeisterschaften",
            "shortName": "Quali",
            "hierarchyLevel": "3"
          },
          "fullHierarchy": {
            "hierarchy": [
              {
                "id": "67565864",
                "name": "Quali-Turniere Jugendmeisterschaften",
                "shortName": "Quali",
                "hierarchyLevel": "3"
              },
              {
                "id": "67565828",
                "name": "SBVV-Jugendmeisterschaften",
                "shortName": "sbvv_jm",
                "hierarchyLevel": "2"
              },
              {
                "id": "62752642",
                "name": "Jugendspielbetrieb",
                "shortName": "JUG",
                "hierarchyLevel": "1"
              },
              {
                "id": "62752550",
                "name": "Südbadischer Volleyball-Verband (SBVV)",
                "shortName": "SBVV",
                "hierarchyLevel": "0"
              }
            ]
          },
          "association": {
            "name": "Südbadischer Volleyball-Verband",
            "shortName": "SBVV"
          }
        },
        "location": {
          "id": "13906446",
          "name": "Sporthalle Nord-West",
          "street": "Otto-Hahn-Str. 3",
          "extraField": "-",
          "postalCode": "77656",
          "city": "Offenburg",
          "note": "-"
        },
        "referees": null,
        "results": {
          "winner": "2",
          "setPoints": "0:2",
          "ballPoints": "43:51",
          "sets": {
            "set": [
              {
                "number": "1",
                "points": "19:25",
                "winner": "TEAM2",
                "duration": "-"
              },
              {
                "number": "2",
                "points": "24:26",
                "winner": "TEAM2",
                "duration": "-"
              }
            ]
          },
          "verified": "false"
        },
        "spectators": "-",
        "netDuration": "-",
        "dateObject": "2024-01-27T12:00:00.000Z",
        "dateIso": "2024-01-27T12:00:00.000Z"
      },
      {
        "id": "67893115",
        "uuid": "15216c16-0fe6-4e41-af74-7a766fa38a69",
        "number": "9",
        "date": "27.01.2024",
        "time": "13:00",
        "delayPossible": "false",
        "decidingMatch": "false",
        "indefinitelyRescheduled": "false",
        "gameReassessed": "false",
        "host": {
          "id": "67669417",
          "uuid": "58963060-8036-49f6-a872-42d3db12ff7c",
          "name": "VC Offenburg 1",
          "club": "VC Offenburg"
        },
        "team": [
          {
            "number": "1",
            "id": "67669418",
            "uuid": "b73f1c49-975d-4e3b-9106-e5fa8d801738",
            "seasonTeamId": "27860236",
            "name": "VC Weil",
            "shortName": null,
            "clubCode": null,
            "club": {
              "name": "VC Weil",
              "shortName": null
            }
          },
          {
            "number": "2",
            "id": "67669419",
            "uuid": "3ee8859f-1226-41e1-9076-befe50cb7134",
            "seasonTeamId": "27860241",
            "name": "FT 1844 Freiburg 1",
            "shortName": "FT 1844 1",
            "clubCode": null,
            "club": {
              "name": "FT 1844 Freiburg",
              "shortName": null
            }
          }
        ],
        "matchSeries": {
          "id": "67565880",
          "uuid": "e945695f-d642-4cd3-886d-2c679cc45681",
          "allSeasonId": "27a326bf-f46a-4e4c-92a4-4f6c43b99ca8",
          "name": "U14 weiblich - Quali 1 am 27.1.24",
          "shortName": "Q2_U14_w",
          "type": "Competition",
          "updated": "2024-03-04 14:54:24.91",
          "structureUpdated": "2024-01-29 11:43:53.347",
          "resultsUpdated": "2024-01-27 17:01:10.752",
          "season": {
            "id": "52761843",
            "uuid": "dfcaac22-776e-4c3c-b3a8-0c34c5a51558",
            "name": "2023/24"
          },
          "hierarchy": {
            "id": "67565864",
            "uuid": "ad1e803f-1985-4939-a566-168d4440881b",
            "name": "Quali-Turniere Jugendmeisterschaften",
            "shortName": "Quali",
            "hierarchyLevel": "3"
          },
          "fullHierarchy": {
            "hierarchy": [
              {
                "id": "67565864",
                "name": "Quali-Turniere Jugendmeisterschaften",
                "shortName": "Quali",
                "hierarchyLevel": "3"
              },
              {
                "id": "67565828",
                "name": "SBVV-Jugendmeisterschaften",
                "shortName": "sbvv_jm",
                "hierarchyLevel": "2"
              },
              {
                "id": "62752642",
                "name": "Jugendspielbetrieb",
                "shortName": "JUG",
                "hierarchyLevel": "1"
              },
              {
                "id": "62752550",
                "name": "Südbadischer Volleyball-Verband (SBVV)",
                "shortName": "SBVV",
                "hierarchyLevel": "0"
              }
            ]
          },
          "association": {
            "name": "Südbadischer Volleyball-Verband",
            "shortName": "SBVV"
          }
        },
        "location": {
          "id": "13906446",
          "name": "Sporthalle Nord-West",
          "street": "Otto-Hahn-Str. 3",
          "extraField": "-",
          "postalCode": "77656",
          "city": "Offenburg",
          "note": "-"
        },
        "referees": null,
        "results": {
          "winner": "1",
          "setPoints": "2:1",
          "ballPoints": "64:55",
          "sets": {
            "set": [
              {
                "number": "1",
                "points": "25:18",
                "winner": "TEAM1",
                "duration": "-"
              },
              {
                "number": "2",
                "points": "24:26",
                "winner": "TEAM2",
                "duration": "-"
              },
              {
                "number": "3",
                "points": "15:11",
                "winner": "TEAM1",
                "duration": "-"
              }
            ]
          },
          "verified": "false"
        },
        "spectators": "-",
        "netDuration": "-",
        "dateObject": "2024-01-27T12:00:00.000Z",
        "dateIso": "2024-01-27T12:00:00.000Z"
      },
      {
        "id": "67893102",
        "uuid": "43b60e64-cdfe-4d5f-850d-896dde9d4eb5",
        "number": "6",
        "date": "27.01.2024",
        "time": "14:00",
        "delayPossible": "false",
        "decidingMatch": "false",
        "indefinitelyRescheduled": "false",
        "gameReassessed": "false",
        "host": {
          "id": "67669417",
          "uuid": "58963060-8036-49f6-a872-42d3db12ff7c",
          "name": "VC Offenburg 1",
          "club": "VC Offenburg"
        },
        "team": [
          {
            "number": "1",
            "id": "67669414",
            "uuid": "1621288b-2251-4797-a9c2-66ac1d1b2d3b",
            "seasonTeamId": "27860249",
            "name": "FT 1844 Freiburg 2",
            "shortName": "FT 1844 2",
            "clubCode": null,
            "club": {
              "name": "FT 1844 Freiburg",
              "shortName": null
            }
          },
          {
            "number": "2",
            "id": "67669416",
            "uuid": "f16afa47-a512-49d0-aa1d-847578faaefe",
            "seasonTeamId": "27860239",
            "name": "VC Müllheim",
            "shortName": null,
            "clubCode": null,
            "club": {
              "name": "VC Müllheim",
              "shortName": null
            }
          }
        ],
        "matchSeries": {
          "id": "67565880",
          "uuid": "e945695f-d642-4cd3-886d-2c679cc45681",
          "allSeasonId": "27a326bf-f46a-4e4c-92a4-4f6c43b99ca8",
          "name": "U14 weiblich - Quali 1 am 27.1.24",
          "shortName": "Q2_U14_w",
          "type": "Competition",
          "updated": "2024-03-04 14:54:24.91",
          "structureUpdated": "2024-01-29 11:43:53.347",
          "resultsUpdated": "2024-01-27 17:01:10.752",
          "season": {
            "id": "52761843",
            "uuid": "dfcaac22-776e-4c3c-b3a8-0c34c5a51558",
            "name": "2023/24"
          },
          "hierarchy": {
            "id": "67565864",
            "uuid": "ad1e803f-1985-4939-a566-168d4440881b",
            "name": "Quali-Turniere Jugendmeisterschaften",
            "shortName": "Quali",
            "hierarchyLevel": "3"
          },
          "fullHierarchy": {
            "hierarchy": [
              {
                "id": "67565864",
                "name": "Quali-Turniere Jugendmeisterschaften",
                "shortName": "Quali",
                "hierarchyLevel": "3"
              },
              {
                "id": "67565828",
                "name": "SBVV-Jugendmeisterschaften",
                "shortName": "sbvv_jm",
                "hierarchyLevel": "2"
              },
              {
                "id": "62752642",
                "name": "Jugendspielbetrieb",
                "shortName": "JUG",
                "hierarchyLevel": "1"
              },
              {
                "id": "62752550",
                "name": "Südbadischer Volleyball-Verband (SBVV)",
                "shortName": "SBVV",
                "hierarchyLevel": "0"
              }
            ]
          },
          "association": {
            "name": "Südbadischer Volleyball-Verband",
            "shortName": "SBVV"
          }
        },
        "location": {
          "id": "13906446",
          "name": "Sporthalle Nord-West",
          "street": "Otto-Hahn-Str. 3",
          "extraField": "-",
          "postalCode": "77656",
          "city": "Offenburg",
          "note": "-"
        },
        "referees": null,
        "results": {
          "winner": "1",
          "setPoints": "2:0",
          "ballPoints": "50:30",
          "sets": {
            "set": [
              {
                "number": "1",
                "points": "25:13",
                "winner": "TEAM1",
                "duration": "-"
              },
              {
                "number": "2",
                "points": "25:17",
                "winner": "TEAM1",
                "duration": "-"
              }
            ]
          },
          "verified": "false"
        },
        "spectators": "-",
        "netDuration": "-",
        "dateObject": "2024-01-27T13:00:00.000Z",
        "dateIso": "2024-01-27T13:00:00.000Z"
      },
      {
        "id": "67893120",
        "uuid": "625cd604-0d2d-44dc-b5aa-bbe5f2969c94",
        "number": "10",
        "date": "27.01.2024",
        "time": "15:00",
        "delayPossible": "false",
        "decidingMatch": "false",
        "indefinitelyRescheduled": "false",
        "gameReassessed": "false",
        "host": {
          "id": "67669417",
          "uuid": "58963060-8036-49f6-a872-42d3db12ff7c",
          "name": "VC Offenburg 1",
          "club": "VC Offenburg"
        },
        "team": [
          {
            "number": "1",
            "id": "67669414",
            "uuid": "1621288b-2251-4797-a9c2-66ac1d1b2d3b",
            "seasonTeamId": "27860249",
            "name": "FT 1844 Freiburg 2",
            "shortName": "FT 1844 2",
            "clubCode": null,
            "club": {
              "name": "FT 1844 Freiburg",
              "shortName": null
            }
          },
          {
            "number": "2",
            "id": "67669418",
            "uuid": "b73f1c49-975d-4e3b-9106-e5fa8d801738",
            "seasonTeamId": "27860236",
            "name": "VC Weil",
            "shortName": null,
            "clubCode": null,
            "club": {
              "name": "VC Weil",
              "shortName": null
            }
          }
        ],
        "matchSeries": {
          "id": "67565880",
          "uuid": "e945695f-d642-4cd3-886d-2c679cc45681",
          "allSeasonId": "27a326bf-f46a-4e4c-92a4-4f6c43b99ca8",
          "name": "U14 weiblich - Quali 1 am 27.1.24",
          "shortName": "Q2_U14_w",
          "type": "Competition",
          "updated": "2024-03-04 14:54:24.91",
          "structureUpdated": "2024-01-29 11:43:53.347",
          "resultsUpdated": "2024-01-27 17:01:10.752",
          "season": {
            "id": "52761843",
            "uuid": "dfcaac22-776e-4c3c-b3a8-0c34c5a51558",
            "name": "2023/24"
          },
          "hierarchy": {
            "id": "67565864",
            "uuid": "ad1e803f-1985-4939-a566-168d4440881b",
            "name": "Quali-Turniere Jugendmeisterschaften",
            "shortName": "Quali",
            "hierarchyLevel": "3"
          },
          "fullHierarchy": {
            "hierarchy": [
              {
                "id": "67565864",
                "name": "Quali-Turniere Jugendmeisterschaften",
                "shortName": "Quali",
                "hierarchyLevel": "3"
              },
              {
                "id": "67565828",
                "name": "SBVV-Jugendmeisterschaften",
                "shortName": "sbvv_jm",
                "hierarchyLevel": "2"
              },
              {
                "id": "62752642",
                "name": "Jugendspielbetrieb",
                "shortName": "JUG",
                "hierarchyLevel": "1"
              },
              {
                "id": "62752550",
                "name": "Südbadischer Volleyball-Verband (SBVV)",
                "shortName": "SBVV",
                "hierarchyLevel": "0"
              }
            ]
          },
          "association": {
            "name": "Südbadischer Volleyball-Verband",
            "shortName": "SBVV"
          }
        },
        "location": {
          "id": "13906446",
          "name": "Sporthalle Nord-West",
          "street": "Otto-Hahn-Str. 3",
          "extraField": "-",
          "postalCode": "77656",
          "city": "Offenburg",
          "note": "-"
        },
        "referees": null,
        "results": {
          "winner": "1",
          "setPoints": "2:0",
          "ballPoints": "50:16",
          "sets": {
            "set": [
              {
                "number": "1",
                "points": "25:7",
                "winner": "TEAM1",
                "duration": "-"
              },
              {
                "number": "2",
                "points": "25:9",
                "winner": "TEAM1",
                "duration": "-"
              }
            ]
          },
          "verified": "false"
        },
        "spectators": "-",
        "netDuration": "-",
        "dateObject": "2024-01-27T14:00:00.000Z",
        "dateIso": "2024-01-27T14:00:00.000Z"
      },
      {
        "id": "67893124",
        "uuid": "7810d2ba-d451-481d-8e8e-37098e79f730",
        "number": "11",
        "date": "27.01.2024",
        "time": "15:00",
        "delayPossible": "false",
        "decidingMatch": "false",
        "indefinitelyRescheduled": "false",
        "gameReassessed": "false",
        "host": {
          "id": "67669417",
          "uuid": "58963060-8036-49f6-a872-42d3db12ff7c",
          "name": "VC Offenburg 1",
          "club": "VC Offenburg"
        },
        "team": [
          {
            "number": "1",
            "id": "67669417",
            "uuid": "58963060-8036-49f6-a872-42d3db12ff7c",
            "seasonTeamId": "27860243",
            "name": "VC Offenburg 1",
            "shortName": null,
            "clubCode": null,
            "club": {
              "name": "VC Offenburg",
              "shortName": null
            }
          },
          {
            "number": "2",
            "id": "67669416",
            "uuid": "f16afa47-a512-49d0-aa1d-847578faaefe",
            "seasonTeamId": "27860239",
            "name": "VC Müllheim",
            "shortName": null,
            "clubCode": null,
            "club": {
              "name": "VC Müllheim",
              "shortName": null
            }
          }
        ],
        "matchSeries": {
          "id": "67565880",
          "uuid": "e945695f-d642-4cd3-886d-2c679cc45681",
          "allSeasonId": "27a326bf-f46a-4e4c-92a4-4f6c43b99ca8",
          "name": "U14 weiblich - Quali 1 am 27.1.24",
          "shortName": "Q2_U14_w",
          "type": "Competition",
          "updated": "2024-03-04 14:54:24.91",
          "structureUpdated": "2024-01-29 11:43:53.347",
          "resultsUpdated": "2024-01-27 17:01:10.752",
          "season": {
            "id": "52761843",
            "uuid": "dfcaac22-776e-4c3c-b3a8-0c34c5a51558",
            "name": "2023/24"
          },
          "hierarchy": {
            "id": "67565864",
            "uuid": "ad1e803f-1985-4939-a566-168d4440881b",
            "name": "Quali-Turniere Jugendmeisterschaften",
            "shortName": "Quali",
            "hierarchyLevel": "3"
          },
          "fullHierarchy": {
            "hierarchy": [
              {
                "id": "67565864",
                "name": "Quali-Turniere Jugendmeisterschaften",
                "shortName": "Quali",
                "hierarchyLevel": "3"
              },
              {
                "id": "67565828",
                "name": "SBVV-Jugendmeisterschaften",
                "shortName": "sbvv_jm",
                "hierarchyLevel": "2"
              },
              {
                "id": "62752642",
                "name": "Jugendspielbetrieb",
                "shortName": "JUG",
                "hierarchyLevel": "1"
              },
              {
                "id": "62752550",
                "name": "Südbadischer Volleyball-Verband (SBVV)",
                "shortName": "SBVV",
                "hierarchyLevel": "0"
              }
            ]
          },
          "association": {
            "name": "Südbadischer Volleyball-Verband",
            "shortName": "SBVV"
          }
        },
        "location": {
          "id": "13906446",
          "name": "Sporthalle Nord-West",
          "street": "Otto-Hahn-Str. 3",
          "extraField": "-",
          "postalCode": "77656",
          "city": "Offenburg",
          "note": "-"
        },
        "referees": null,
        "results": {
          "winner": "1",
          "setPoints": "2:0",
          "ballPoints": "50:21",
          "sets": {
            "set": [
              {
                "number": "1",
                "points": "25:12",
                "winner": "TEAM1",
                "duration": "-"
              },
              {
                "number": "2",
                "points": "25:9",
                "winner": "TEAM1",
                "duration": "-"
              }
            ]
          },
          "verified": "false"
        },
        "spectators": "-",
        "netDuration": "-",
        "dateObject": "2024-01-27T14:00:00.000Z",
        "dateIso": "2024-01-27T14:00:00.000Z"
      },
      {
        "id": "67893133",
        "uuid": "d005c0e8-674d-4c3c-8a48-ac8ac4d0b95e",
        "number": "15",
        "date": "27.01.2024",
        "time": "16:00",
        "delayPossible": "false",
        "decidingMatch": "false",
        "indefinitelyRescheduled": "false",
        "gameReassessed": "false",
        "host": {
          "id": "67669417",
          "uuid": "58963060-8036-49f6-a872-42d3db12ff7c",
          "name": "VC Offenburg 1",
          "club": "VC Offenburg"
        },
        "team": [
          {
            "number": "1",
            "id": "67669418",
            "uuid": "b73f1c49-975d-4e3b-9106-e5fa8d801738",
            "seasonTeamId": "27860236",
            "name": "VC Weil",
            "shortName": null,
            "clubCode": null,
            "club": {
              "name": "VC Weil",
              "shortName": null
            }
          },
          {
            "number": "2",
            "id": "67669416",
            "uuid": "f16afa47-a512-49d0-aa1d-847578faaefe",
            "seasonTeamId": "27860239",
            "name": "VC Müllheim",
            "shortName": null,
            "clubCode": null,
            "club": {
              "name": "VC Müllheim",
              "shortName": null
            }
          }
        ],
        "matchSeries": {
          "id": "67565880",
          "uuid": "e945695f-d642-4cd3-886d-2c679cc45681",
          "allSeasonId": "27a326bf-f46a-4e4c-92a4-4f6c43b99ca8",
          "name": "U14 weiblich - Quali 1 am 27.1.24",
          "shortName": "Q2_U14_w",
          "type": "Competition",
          "updated": "2024-03-04 14:54:24.91",
          "structureUpdated": "2024-01-29 11:43:53.347",
          "resultsUpdated": "2024-01-27 17:01:10.752",
          "season": {
            "id": "52761843",
            "uuid": "dfcaac22-776e-4c3c-b3a8-0c34c5a51558",
            "name": "2023/24"
          },
          "hierarchy": {
            "id": "67565864",
            "uuid": "ad1e803f-1985-4939-a566-168d4440881b",
            "name": "Quali-Turniere Jugendmeisterschaften",
            "shortName": "Quali",
            "hierarchyLevel": "3"
          },
          "fullHierarchy": {
            "hierarchy": [
              {
                "id": "67565864",
                "name": "Quali-Turniere Jugendmeisterschaften",
                "shortName": "Quali",
                "hierarchyLevel": "3"
              },
              {
                "id": "67565828",
                "name": "SBVV-Jugendmeisterschaften",
                "shortName": "sbvv_jm",
                "hierarchyLevel": "2"
              },
              {
                "id": "62752642",
                "name": "Jugendspielbetrieb",
                "shortName": "JUG",
                "hierarchyLevel": "1"
              },
              {
                "id": "62752550",
                "name": "Südbadischer Volleyball-Verband (SBVV)",
                "shortName": "SBVV",
                "hierarchyLevel": "0"
              }
            ]
          },
          "association": {
            "name": "Südbadischer Volleyball-Verband",
            "shortName": "SBVV"
          }
        },
        "location": {
          "id": "13906446",
          "name": "Sporthalle Nord-West",
          "street": "Otto-Hahn-Str. 3",
          "extraField": "-",
          "postalCode": "77656",
          "city": "Offenburg",
          "note": "-"
        },
        "referees": null,
        "results": {
          "winner": "2",
          "setPoints": "0:2",
          "ballPoints": "32:50",
          "sets": {
            "set": [
              {
                "number": "1",
                "points": "15:25",
                "winner": "TEAM2",
                "duration": "-"
              },
              {
                "number": "2",
                "points": "17:25",
                "winner": "TEAM2",
                "duration": "-"
              }
            ]
          },
          "verified": "false"
        },
        "spectators": "-",
        "netDuration": "-",
        "dateObject": "2024-01-27T15:00:00.000Z",
        "dateIso": "2024-01-27T15:00:00.000Z"
      },
      {
        "id": "67893129",
        "uuid": "f17a35c7-94f2-4248-9c9b-03de6c052cb7",
        "number": "14",
        "date": "27.01.2024",
        "time": "16:00",
        "delayPossible": "false",
        "decidingMatch": "false",
        "indefinitelyRescheduled": "false",
        "gameReassessed": "false",
        "host": {
          "id": "67669417",
          "uuid": "58963060-8036-49f6-a872-42d3db12ff7c",
          "name": "VC Offenburg 1",
          "club": "VC Offenburg"
        },
        "team": [
          {
            "number": "1",
            "id": "67669421",
            "uuid": "336bb69c-c80c-4160-aeb2-bbbfdf163d4a",
            "seasonTeamId": "27860247",
            "name": "VfR Umkirch",
            "shortName": null,
            "clubCode": null,
            "club": {
              "name": "VfR Umkirch",
              "shortName": null
            }
          },
          {
            "number": "2",
            "id": "67669419",
            "uuid": "3ee8859f-1226-41e1-9076-befe50cb7134",
            "seasonTeamId": "27860241",
            "name": "FT 1844 Freiburg 1",
            "shortName": "FT 1844 1",
            "clubCode": null,
            "club": {
              "name": "FT 1844 Freiburg",
              "shortName": null
            }
          }
        ],
        "matchSeries": {
          "id": "67565880",
          "uuid": "e945695f-d642-4cd3-886d-2c679cc45681",
          "allSeasonId": "27a326bf-f46a-4e4c-92a4-4f6c43b99ca8",
          "name": "U14 weiblich - Quali 1 am 27.1.24",
          "shortName": "Q2_U14_w",
          "type": "Competition",
          "updated": "2024-03-04 14:54:24.91",
          "structureUpdated": "2024-01-29 11:43:53.347",
          "resultsUpdated": "2024-01-27 17:01:10.752",
          "season": {
            "id": "52761843",
            "uuid": "dfcaac22-776e-4c3c-b3a8-0c34c5a51558",
            "name": "2023/24"
          },
          "hierarchy": {
            "id": "67565864",
            "uuid": "ad1e803f-1985-4939-a566-168d4440881b",
            "name": "Quali-Turniere Jugendmeisterschaften",
            "shortName": "Quali",
            "hierarchyLevel": "3"
          },
          "fullHierarchy": {
            "hierarchy": [
              {
                "id": "67565864",
                "name": "Quali-Turniere Jugendmeisterschaften",
                "shortName": "Quali",
                "hierarchyLevel": "3"
              },
              {
                "id": "67565828",
                "name": "SBVV-Jugendmeisterschaften",
                "shortName": "sbvv_jm",
                "hierarchyLevel": "2"
              },
              {
                "id": "62752642",
                "name": "Jugendspielbetrieb",
                "shortName": "JUG",
                "hierarchyLevel": "1"
              },
              {
                "id": "62752550",
                "name": "Südbadischer Volleyball-Verband (SBVV)",
                "shortName": "SBVV",
                "hierarchyLevel": "0"
              }
            ]
          },
          "association": {
            "name": "Südbadischer Volleyball-Verband",
            "shortName": "SBVV"
          }
        },
        "location": {
          "id": "13906446",
          "name": "Sporthalle Nord-West",
          "street": "Otto-Hahn-Str. 3",
          "extraField": "-",
          "postalCode": "77656",
          "city": "Offenburg",
          "note": "-"
        },
        "referees": null,
        "results": {
          "winner": "1",
          "setPoints": "2:0",
          "ballPoints": "50:34",
          "sets": {
            "set": [
              {
                "number": "1",
                "points": "25:14",
                "winner": "TEAM1",
                "duration": "-"
              },
              {
                "number": "2",
                "points": "25:20",
                "winner": "TEAM1",
                "duration": "-"
              }
            ]
          },
          "verified": "false"
        },
        "spectators": "-",
        "netDuration": "-",
        "dateObject": "2024-01-27T15:00:00.000Z",
        "dateIso": "2024-01-27T15:00:00.000Z"
      },
      {
        "id": "67893137",
        "uuid": "703b6690-05a9-4964-a0d3-d418dd8c1754",
        "number": "16",
        "date": "27.01.2024",
        "time": "17:00",
        "delayPossible": "false",
        "decidingMatch": "false",
        "indefinitelyRescheduled": "false",
        "gameReassessed": "false",
        "host": {
          "id": "67669417",
          "uuid": "58963060-8036-49f6-a872-42d3db12ff7c",
          "name": "VC Offenburg 1",
          "club": "VC Offenburg"
        },
        "team": [
          {
            "number": "1",
            "id": "67669414",
            "uuid": "1621288b-2251-4797-a9c2-66ac1d1b2d3b",
            "seasonTeamId": "27860249",
            "name": "FT 1844 Freiburg 2",
            "shortName": "FT 1844 2",
            "clubCode": null,
            "club": {
              "name": "FT 1844 Freiburg",
              "shortName": null
            }
          },
          {
            "number": "2",
            "id": "67669417",
            "uuid": "58963060-8036-49f6-a872-42d3db12ff7c",
            "seasonTeamId": "27860243",
            "name": "VC Offenburg 1",
            "shortName": null,
            "clubCode": null,
            "club": {
              "name": "VC Offenburg",
              "shortName": null
            }
          }
        ],
        "matchSeries": {
          "id": "67565880",
          "uuid": "e945695f-d642-4cd3-886d-2c679cc45681",
          "allSeasonId": "27a326bf-f46a-4e4c-92a4-4f6c43b99ca8",
          "name": "U14 weiblich - Quali 1 am 27.1.24",
          "shortName": "Q2_U14_w",
          "type": "Competition",
          "updated": "2024-03-04 14:54:24.91",
          "structureUpdated": "2024-01-29 11:43:53.347",
          "resultsUpdated": "2024-01-27 17:01:10.752",
          "season": {
            "id": "52761843",
            "uuid": "dfcaac22-776e-4c3c-b3a8-0c34c5a51558",
            "name": "2023/24"
          },
          "hierarchy": {
            "id": "67565864",
            "uuid": "ad1e803f-1985-4939-a566-168d4440881b",
            "name": "Quali-Turniere Jugendmeisterschaften",
            "shortName": "Quali",
            "hierarchyLevel": "3"
          },
          "fullHierarchy": {
            "hierarchy": [
              {
                "id": "67565864",
                "name": "Quali-Turniere Jugendmeisterschaften",
                "shortName": "Quali",
                "hierarchyLevel": "3"
              },
              {
                "id": "67565828",
                "name": "SBVV-Jugendmeisterschaften",
                "shortName": "sbvv_jm",
                "hierarchyLevel": "2"
              },
              {
                "id": "62752642",
                "name": "Jugendspielbetrieb",
                "shortName": "JUG",
                "hierarchyLevel": "1"
              },
              {
                "id": "62752550",
                "name": "Südbadischer Volleyball-Verband (SBVV)",
                "shortName": "SBVV",
                "hierarchyLevel": "0"
              }
            ]
          },
          "association": {
            "name": "Südbadischer Volleyball-Verband",
            "shortName": "SBVV"
          }
        },
        "location": {
          "id": "13906446",
          "name": "Sporthalle Nord-West",
          "street": "Otto-Hahn-Str. 3",
          "extraField": "-",
          "postalCode": "77656",
          "city": "Offenburg",
          "note": "-"
        },
        "referees": null,
        "results": {
          "winner": "2",
          "setPoints": "0:2",
          "ballPoints": "25:50",
          "sets": {
            "set": [
              {
                "number": "1",
                "points": "14:25",
                "winner": "TEAM2",
                "duration": "-"
              },
              {
                "number": "2",
                "points": "11:25",
                "winner": "TEAM2",
                "duration": "-"
              }
            ]
          },
          "verified": "false"
        },
        "spectators": "-",
        "netDuration": "-",
        "dateObject": "2024-01-27T16:00:00.000Z",
        "dateIso": "2024-01-27T16:00:00.000Z"
      }
    ]
  }
}